confusionflow/__init__.py
confusionflow/_version.py
confusionflow/utils.py
confusionflow/logging/__init__.py
confusionflow/logging/callbacks.py
confusionflow/logging/fold.py
confusionflow/logging/foldlog.py
confusionflow/logging/foldlogdata.py
confusionflow/logging/logfunction.py
confusionflow/logging/run.py
confusionflow/logging/utils.py
confusionflow/server/__init__.py
confusionflow/server/utils.py
confusionflow/server/blueprints/__init__.py
confusionflow/server/blueprints/api.py
confusionflow/server/blueprints/web.py
confusionflow/static/06ff8640532902ee7a6f.js
confusionflow/static/404.html-loader
confusionflow/static/448c34a56d699c29117adc64c43affeb.woff2
confusionflow/static/487372d816956e6778f1.js
confusionflow/static/55643c20177e5b2ad1c9.js
confusionflow/static/674f50d287a8c48dc19ba404d20fe713.eot
confusionflow/static/7017b1678bfa60472528.js
confusionflow/static/70a73236ca1f9522b517.js
confusionflow/static/7621d4e2be395e9efe9d.js
confusionflow/static/89889688147bd7575d6327160d64e760.svg
confusionflow/static/8eada5ada219af82eeb3.js
confusionflow/static/912ec66d7572ff821749319396470bde.svg
confusionflow/static/ac3ce59be2b9faa43f31.js
confusionflow/static/af7ae505a9eed503f8b8e6982036873e.woff2
confusionflow/static/android-chrome-192x192.png
confusionflow/static/android-chrome-384x384.png
confusionflow/static/app.js
confusionflow/static/apple-touch-icon.png
confusionflow/static/b06871f281fee6b241d60582ae9369b9.ttf
confusionflow/static/b538229d72d8bbcbebca.js
confusionflow/static/browserconfig.xml
confusionflow/static/buildInfo.json
confusionflow/static/c5cb8c3a01288061c565.js
confusionflow/static/c6205717f91a614ce454.js
confusionflow/static/common.js
confusionflow/static/e18bbf611f2a2e43afc071aa2f4e1512.ttf
confusionflow/static/e5556ac678fdc9bbe7e1.js
confusionflow/static/eac392a2f77243b828e4.js
confusionflow/static/f4769f9bdb7466be65088239c12046d1.eot
confusionflow/static/fa2772327f55d8198301fdb8bcfc8158.woff
confusionflow/static/favicon-16x16.png
confusionflow-0.1.3.dist-info/LICENSE
confusionflow-0.1.3.dist-info/METADATA
confusionflow-0.1.3.dist-info/WHEEL
confusionflow-0.1.3.dist-info/entry_points.txt
confusionflow-0.1.3.dist-info/top_level.txt
confusionflow-0.1.3.dist-info/RECORD
