Metadata-Version: 2.1
Name: confusionflow
Version: 0.1.3
Summary: ConfusionFlow is a visualization tool that enables more nuanced monitoring of a neural network's training process.
Home-page: https://github.com/confusionflow/confusionflow
Author: ConfusionFlow Contributors
Author-email: gfrogat@gmail.com
License: BSD-3-Clause
Project-URL: Documentation, https://docs.confusionflow.org
Project-URL: Source, https://github.com/confusionflow/confusionflow/
Project-URL: Tracker, https://github.com/confusionflow/confusionflow/issues
Platform: UNKNOWN
Requires-Dist: flask
Requires-Dist: gevent
Requires-Dist: pyyaml
